MANIFEST.in
README.rst
setup.py
djangocms_career/__init__.py
djangocms_career/__init__.pyc
djangocms_career/admin.py
djangocms_career/admin.pyc
djangocms_career/cms_plugins.py
djangocms_career/cms_plugins.pyc
djangocms_career/models.py
djangocms_career/models.pyc
djangocms_career/tests.py
djangocms_career/tests.pyc
djangocms_career/urls.py
djangocms_career/views.py
djangocms_career.egg-info/PKG-INFO
djangocms_career.egg-info/SOURCES.txt
djangocms_career.egg-info/dependency_links.txt
djangocms_career.egg-info/not-zip-safe
djangocms_career.egg-info/requires.txt
djangocms_career.egg-info/top_level.txt
djangocms_career/locale/de/LC_MESSAGES/django.po
djangocms_career/locale/en/LC_MESSAGES/django.po
djangocms_career/migrations/0001_initial.py
djangocms_career/migrations/0001_initial.pyc
djangocms_career/migrations/0002_positionplugin.py
djangocms_career/migrations/0002_positionplugin.pyc
djangocms_career/migrations/0003_auto_20160418_1143.py
djangocms_career/migrations/0003_auto_20160418_1143.pyc
djangocms_career/migrations/0004_auto_20160418_1145.py
djangocms_career/migrations/0004_auto_20160418_1145.pyc
djangocms_career/migrations/0005_auto_20160418_1202.py
djangocms_career/migrations/0005_auto_20160418_1202.pyc
djangocms_career/migrations/0006_remove_post_is_public.py
djangocms_career/migrations/0006_remove_post_is_public.pyc
djangocms_career/migrations/0007_auto_20160418_1325.py
djangocms_career/migrations/0007_auto_20160418_1325.pyc
djangocms_career/migrations/0008_auto_20160418_1514.py
djangocms_career/migrations/0008_auto_20160418_1514.pyc
djangocms_career/migrations/__init__.py
djangocms_career/migrations/__init__.pyc
djangocms_career/static/djangocms_career/css/style.css
djangocms_career/templates/djangocms_career/career_plugin.html
djangocms_career/templates/djangocms_career/position_object.html