Metadata-Version: 1.1
Name: djangocms-career
Version: 0.1.2
Summary: Django CMS Plugin to showcase a career or educational paths on portfolio and CV-Websites.
Home-page: https://github.com/dmonn/djangocms-career/
Author: Dominic Monn
Author-email: monn.dominic@gmail.com
License: BSD License
Platform: OS Independent
Classifier: Environment :: Web Environment
Classifier: Framework :: Django
Classifier: Intended Audience :: Developers
Classifier: License :: OSI Approved :: BSD License
Classifier: Operating System :: OS Independent
Classifier: Programming Language :: Python
Classifier: Programming Language :: Python :: 2
Classifier: Programming Language :: Python :: 3
Classifier: Topic :: Software Development :: Libraries :: Application Frameworks
Classifier: Topic :: Internet :: WWW/HTTP :: Dynamic Content
